bittrade_cryptodotcom_websocket/__init__.py
bittrade_cryptodotcom_websocket/channels/__init__.py
bittrade_cryptodotcom_websocket/channels/channels.py
bittrade_cryptodotcom_websocket/channels/models/__init__.py
bittrade_cryptodotcom_websocket/channels/models/spread.py
bittrade_cryptodotcom_websocket/channels/models/ticker.py
bittrade_cryptodotcom_websocket/channels/open_orders.py
bittrade_cryptodotcom_websocket/channels/orderbook.py
bittrade_cryptodotcom_websocket/channels/own_trades.py
bittrade_cryptodotcom_websocket/channels/spread.py
bittrade_cryptodotcom_websocket/channels/subscribe.py
bittrade_cryptodotcom_websocket/channels/ticker.py
bittrade_cryptodotcom_websocket/connection/__init__.py
bittrade_cryptodotcom_websocket/connection/connection_operators.py
bittrade_cryptodotcom_websocket/connection/generic.py
bittrade_cryptodotcom_websocket/connection/http.py
bittrade_cryptodotcom_websocket/connection/private.py
bittrade_cryptodotcom_websocket/connection/public.py
bittrade_cryptodotcom_websocket/connection/reconnect.py
bittrade_cryptodotcom_websocket/connection/request_response.py
bittrade_cryptodotcom_websocket/events/__init__.py
bittrade_cryptodotcom_websocket/events/ids.py
bittrade_cryptodotcom_websocket/events/message.py
bittrade_cryptodotcom_websocket/events/methods.py
bittrade_cryptodotcom_websocket/events/models/__init__.py
bittrade_cryptodotcom_websocket/events/models/order.py
bittrade_cryptodotcom_websocket/framework/__init__.py
bittrade_cryptodotcom_websocket/framework/context_manager.py
bittrade_cryptodotcom_websocket/framework/framework.py
bittrade_cryptodotcom_websocket/framework/logging.py
bittrade_cryptodotcom_websocket/messages/__init__.py
bittrade_cryptodotcom_websocket/messages/filters/__init__.py
bittrade_cryptodotcom_websocket/messages/filters/kind.py
bittrade_cryptodotcom_websocket/messages/heartbeat.py
bittrade_cryptodotcom_websocket/messages/json.py
bittrade_cryptodotcom_websocket/messages/listen.py
bittrade_cryptodotcom_websocket-0.2.2.dist-info/METADATA
bittrade_cryptodotcom_websocket-0.2.2.dist-info/WHEEL
bittrade_cryptodotcom_websocket-0.2.2.dist-info/RECORD
