Metadata-Version: 2.1
Name: bittrade-cryptodotcom-websocket
Version: 0.2.2
Summary: Reactive Websocket for Crypto.com
Home-page: https://github.com/TechSpaceAsia/bittrade-cryptodotcom-websocket
License: MIT
Author: mat
Author-email: matt@techspace.asia
Requires-Python: >=3.10,<4.0
Classifier: Development Status :: 3 - Alpha
Classifier: Intended Audience :: Developers
Classifier: License :: OSI Approved :: MIT License
Classifier: Programming Language :: Python :: 3
Classifier: Programming Language :: Python :: 3.10
Classifier: Programming Language :: Python :: 3.11
Classifier: Topic :: Office/Business :: Financial :: Investment
Classifier: Topic :: Software Development :: Libraries :: Python Modules
Requires-Dist: ccxt (>=2.6.5,<3.0.0)
Requires-Dist: elm-framework-helpers (>=0.3.1,<0.4.0)
Requires-Dist: expression (>=4.2.2,<5.0.0)
Requires-Dist: orjson (>=3.8.3,<4.0.0)
Requires-Dist: prompt-toolkit (>=3.0.36,<4.0.0)
Requires-Dist: ptpython (>=3.0.22,<4.0.0)
Requires-Dist: pydantic (>=1.10.4,<2.0.0)
Requires-Dist: reactivex (>=4.0.4,<5.0.0)
Requires-Dist: requests (>=2.28.2,<3.0.0)
Requires-Dist: returns (>=0.19.0,<0.20.0)
Requires-Dist: websocket-client (>=1.4.2,<2.0.0)
Project-URL: Repository, https://github.com/TechSpaceAsia/bittrade-cryptodotcom-websocket
